ottu/__init__.py
ottu/async_ottu.py
ottu/auth.py
ottu/cards.py
ottu/decorators.py
ottu/enums.py
ottu/errors.py
ottu/json.py
ottu/mixins.py
ottu/ottu.py
ottu/request.py
ottu/session.py
ottu/urls.py
ottu/contrib/__init__.py
ottu/contrib/django/__init__.py
ottu/contrib/django/admin.py
ottu/contrib/django/apps.py
ottu/contrib/django/conf.py
ottu/contrib/django/models.py
ottu/contrib/django/views.py
ottu/contrib/django/core/__init__.py
ottu/contrib/django/core/ottu.py
ottu/contrib/django/core/session.py
ottu/contrib/django/migrations/0001_initial.py
ottu/contrib/django/migrations/__init__.py
ottu/utils/__init__.py
ottu/utils/dataclasses.py
ottu/utils/helpers.py
ottu/utils/webhooks.py
ottu_py-1.7.0.dist-info/licenses/LICENSE
ottu_py-1.7.0.dist-info/METADATA
ottu_py-1.7.0.dist-info/WHEEL
ottu_py-1.7.0.dist-info/top_level.txt
ottu_py-1.7.0.dist-info/RECORD
