Metadata-Version: 2.4
Name: ottu-py
Version: 1.7.0
Summary: Python bindings for the Ottu Checkout API
Author-email: Jerin Peter George <jerinpetergeorge@gmail.com>
Project-URL: Homepage, https://github.com/ottuco/ottu-py
Classifier: Environment :: Web Environment
Classifier: Environment :: Console
Classifier: Intended Audience :: Developers
Classifier: Operating System :: OS Independent
Classifier: Programming Language :: Python
Classifier: Programming Language :: Python :: 3.9
Classifier: Programming Language :: Python :: 3.10
Classifier: Topic :: Utilities
Requires-Python: >=3.7
License-File: LICENSE
Requires-Dist: httpx>=0.25.0
Provides-Extra: django
Requires-Dist: django<4.3; extra == "django"
Requires-Dist: asgiref>=3.6.0; extra == "django"
Provides-Extra: async
Requires-Dist: asgiref>=3.6.0; extra == "async"
Provides-Extra: all
Requires-Dist: ottu-py[async,django]; extra == "all"
Provides-Extra: test
Requires-Dist: pytest==7.4.3; extra == "test"
Requires-Dist: pytest-django==4.7.0; extra == "test"
Requires-Dist: pytest-httpx==0.27.0; extra == "test"
Requires-Dist: pytest-cov==4.1.0; extra == "test"
Requires-Dist: pytest-mock==3.12.0; extra == "test"
Requires-Dist: pytest-asyncio==0.21.1; extra == "test"
Provides-Extra: lint-and-formatting
Requires-Dist: black; extra == "lint-and-formatting"
Requires-Dist: flake8; extra == "lint-and-formatting"
Requires-Dist: flake8-print; extra == "lint-and-formatting"
Requires-Dist: isort; extra == "lint-and-formatting"
Requires-Dist: pre-commit; extra == "lint-and-formatting"
Requires-Dist: mypy; extra == "lint-and-formatting"
Provides-Extra: dev
Requires-Dist: ottu-py[all,lint-and-formatting,test]; extra == "dev"
Requires-Dist: bump2version~=1.0.1; extra == "dev"
Dynamic: license-file
